extract_url_from_text/__init__.py
extract_url_from_text/main.py
extract_url_from_text-0.1.1.dist-info/entry_points.txt
extract_url_from_text-0.1.1.dist-info/METADATA
extract_url_from_text-0.1.1.dist-info/WHEEL
extract_url_from_text-0.1.1.dist-info/RECORD
